vivi_analytics_library/__init__.py
vivi_analytics_library/data_services.py
vivi_analytics_library/models.py
vivi_analytics_library/text_analyzer.py
vivi_analytics_library-2.1.1.dist-info/METADATA
vivi_analytics_library-2.1.1.dist-info/WHEEL
vivi_analytics_library-2.1.1.dist-info/top_level.txt
vivi_analytics_library-2.1.1.dist-info/RECORD
