Metadata-Version: 2.4
Name: vivi_analytics_library
Version: 2.1.1
Summary: A library with methods used in data pipelines for analytics and reports.
Author: Developer
Requires-Python: >=3.10
Requires-Dist: aiohttp
Requires-Dist: pydantic
Requires-Dist: openai==1.99.6
Dynamic: author
Dynamic: requires-dist
Dynamic: requires-python
Dynamic: summary
